huilin/__init__.py
huilin/myprint.py
huilinthird-1.0.0.dist-info/METADATA
huilinthird-1.0.0.dist-info/WHEEL
huilinthird-1.0.0.dist-info/top_level.txt
huilinthird-1.0.0.dist-info/RECORD
